cp2kparser/__init__.py
cp2kparser/__version__.py
cp2kparser/parser.py
cp2kparser/py.typed
CP2K_Parser-2.0.0.dist-info/LICENSE
CP2K_Parser-2.0.0.dist-info/METADATA
CP2K_Parser-2.0.0.dist-info/NOTICE
CP2K_Parser-2.0.0.dist-info/WHEEL
CP2K_Parser-2.0.0.dist-info/top_level.txt
CP2K_Parser-2.0.0.dist-info/RECORD
