Metadata-Version: 2.1
Name: CP2K-Parser
Version: 2.0.0
Summary: A package for converting CP2K input files into PLAMS-compatible dictionaries.
Home-page: https://github.com/nlesc-nano/CP2K-Parser
Author: Bas van Beek
Author-email: b.f.van.beek@vu.nl
License: Apache Software License
Keywords: python-3,python-3-7,python-3-8,python-3-9,python-3-10,dictionary,parsing,cp2k,plams
Platform: UNKNOWN
Classifier: Development Status :: 5 - Production/Stable
Classifier: Intended Audience :: Developers
Classifier: Topic :: Software Development :: Libraries
Classifier: License :: OSI Approved :: Apache Software License
Classifier: Natural Language :: English
Classifier: Programming Language :: Python :: 3 :: Only
Classifier: Programming Language :: Python :: 3.7
Classifier: Programming Language :: Python :: 3.8
Classifier: Programming Language :: Python :: 3.9
Classifier: Programming Language :: Python :: 3.10
Classifier: Typing :: Typed
Requires-Python: >=3.7
Provides-Extra: test
Requires-Dist: pytest ; extra == 'test'
Requires-Dist: pytest-cov ; extra == 'test'
Requires-Dist: pytest-flake8 ; extra == 'test'
Requires-Dist: pytest-pydocstyle ; extra == 'test'
